{"title":"MBC M 주간아이돌 ─ 네이버TV","url":"https://tv.naver.com/weekidol/clips","favicon":"https://tv.naver.com/weekidol/favicon.ico","elements":[{"title":"[방송선공개] 요즘 햄스터는 노래도 하네... 비비지 은하가 부르는 윤하의 ＜오늘 헤어졌어요＞♬","contents":"1:32","link":"https://tv.naver.com/v/24985735","retrieved":1644282668756,"image":"https://phinf.pstatic.net/tvcast/20220207_293/adFk0_1644222996618fX03O_JPEG/CA202202090004.jpg?type=f194_109_blend"},{"title":"[방송선공개] 신인그룹 비비지의 팀명 비하인드!","contents":"2:04","link":"https://tv.naver.com/v/24985733","retrieved":1644282668762,"image":"https://phinf.pstatic.net/tvcast/20220207_1/uvnc4_1644222994211b1PnV_JPEG/CA202202090003.jpg?type=f194_109_blend"},{"title":"블핑은 못 참지,, 광란의 파티장 된 케망진창 주간아 x_x","contents":"3:38","link":"https://tv.naver.com/v/24899365","retrieved":1643805119532,"image":"https://phinf.pstatic.net/tvcast/20220202_149/EiMuk_1643803600091RaG3p_JPEG/CA202202020043.jpg?type=f194_109_blend"},{"title":"주간아이돌 548회 예고","contents":"0:30","link":"https://tv.naver.com/v/24899315","retrieved":1643805119534,"image":"https://phinf.pstatic.net/tvcast/20220202_11/mz5Rq_164380329578492leK_JPEG/CA202202090001.jpg?type=f194_109_blend"},{"title":"서영은x김다연x마시로의 NCT127 ＜영웅＞ 댄스","contents":"1:51","link":"https://tv.naver.com/v/24899270","retrieved":1643805119535,"image":"https://phinf.pstatic.net/tvcast/20220202_54/NdNcD_1643803053077fIHiM_JPEG/CA202202020041.jpg?type=f194_109_blend"},{"title":"케플러의 Dreams Come True,,★ (열정 ver.)","contents":"3:26","link":"https://tv.naver.com/v/24899260","retrieved":1643805119536,"image":"https://phinf.pstatic.net/tvcast/20220202_106/3PnmE_1643802999873BVBH9_JPEG/CA202202020038.jpg?type=f194_109_blend"},{"title":"BTS의 ＜Dynamite＞ '엄마와 아이들팀' vs '160즈'","contents":"2:31","link":"https://tv.naver.com/v/24899258","retrieved":1643805119537,"image":"https://phinf.pstatic.net/tvcast/20220202_271/J9v5p_1643802994873Lerxy_JPEG/CA202202020036.jpg?type=f194_109_blend"},{"title":"짱플러의 완벽 퍼포 ITZY ＜LOCO＞ 커버 댄스","contents":"2:11","link":"https://tv.naver.com/v/24899104","retrieved":1643805119538,"image":"https://phinf.pstatic.net/tvcast/20220202_7/jfGRc_1643802153134UPzwz_JPEG/CA202202020032.jpg?type=f194_109_blend"},{"title":"음색요정 채현x영은이 부르는 다비치의 ＜8282＞♬","contents":"1:09","link":"https://tv.naver.com/v/24899026","retrieved":1643805119542,"image":"https://phinf.pstatic.net/tvcast/20220202_184/6Ljvg_1643801819790Q2zlL_JPEG/CA202202020031.jpg?type=f194_109_blend"},{"title":"히카루의 NCT U ＜Misfit＞ 랩 커버","contents":"1:16","link":"https://tv.naver.com/v/24899024","retrieved":1643805119543,"image":"https://phinf.pstatic.net/tvcast/20220202_244/3IOfJ_1643801818665hzSMz_JPEG/CA202202020030.jpg?type=f194_109_blend"},{"title":"[오또케송] 애교 인간 최유진 X 애교 최초 공개 마시로","contents":"2:08","link":"https://tv.naver.com/v/24899023","retrieved":1643805119544,"image":"https://phinf.pstatic.net/tvcast/20220202_211/2bBvd_1643801813619vWDYG_JPEG/CA202202020029.jpg?type=f194_109_blend"},{"title":"샤오팅의 댄스 스포츠 교실 그리고 이상 증상 보이는 수강생들","contents":"2:28","link":"https://tv.naver.com/v/24899010","retrieved":1643805119545,"image":"https://phinf.pstatic.net/tvcast/20220202_143/4jOp4_1643801796273cYyqu_JPEG/CA202202020028.jpg?type=f194_109_blend"},{"title":"다연이는 이걸 해내 '콩순이 오프닝송'을 곁들인 프리 댄스","contents":"2:38","link":"https://tv.naver.com/v/24898933","retrieved":1643805119548,"image":"https://phinf.pstatic.net/tvcast/20220202_138/zDfLs_1643801497121sIteN_JPEG/CA202202020027.jpg?type=f194_109_blend"},{"title":"우리 리더 유진이는요♥ 멋짐 10스푼에 애교 10000스푼 ㅇ3ㅇ","contents":"2:31","link":"https://tv.naver.com/v/24898853","retrieved":1643805119550,"image":"https://phinf.pstatic.net/tvcast/20220202_267/Wjfmz_1643801198660zQ6e1_JPEG/CA202202020026.jpg?type=f194_109_blend"},{"title":"얼굴만 봐도 웃음이 나는 케플러의 숙소 생활 (ft.히히즈)","contents":"2:04","link":"https://tv.naver.com/v/24898852","retrieved":1643805119552,"image":"https://phinf.pstatic.net/tvcast/20220202_244/wkAKW_1643801196859Jyj9F_JPEG/CA202202020025.jpg?type=f194_109_blend"},{"title":"짱플러 예능 에이스들의 only '목소리'로 하는 개인기","contents":"2:37","link":"https://tv.naver.com/v/24898849","retrieved":1643805119553,"image":"https://phinf.pstatic.net/tvcast/20220202_16/hDIlQ_1643801192960AMctC_JPEG/CA202202020024.jpg?type=f194_109_blend"},{"title":"[주간아 직캠] 케플러(kep1er)의 '케이팝 커버 퀴즈' 직캠Ver. l EP.547","contents":"2:24","link":"https://tv.naver.com/v/24898365","retrieved":1643805119554,"image":"https://phinf.pstatic.net/tvcast/20220202_251/0cPFE_1643799095817n8ryM_JPEG/CA202202020022.jpg?type=f194_109_blend"},{"title":"[Weekly Playlist l 4K캠] kep1er - The Boys (케플러 - 더 보이즈 (원곡 : 소녀시대) ) l EP.547","contents":"3:59","link":"https://tv.naver.com/v/24898223","retrieved":1643805119556,"image":"https://phinf.pstatic.net/tvcast/20220202_278/tujOx_1643799698733QtI8y_JPEG/CA202202020008_02.jpg?type=f194_109_blend"},{"title":"[주간아 직캠] 케플러(kep1er) 휴닝바히에의 'XOXO' (원곡 : 전소미) 직캠 Ver. l EP.547","contents":"1:26","link":"https://tv.naver.com/v/24898212","retrieved":1643805119560,"image":"https://phinf.pstatic.net/tvcast/20220202_276/bD1Py_1643798492517mCs3p_JPEG/CA202202020021.jpg?type=f194_109_blend"},{"title":"[Weekly Playlist l 짐벌캠] kep1er - The Boys (케플러 - 더 보이즈 (원곡 : 소녀시대) ) l EP.547","contents":"3:59","link":"https://tv.naver.com/v/24898160","retrieved":1643805119561,"image":"https://phinf.pstatic.net/tvcast/20220202_250/zlQHb_1643798195406RWhqr_JPEG/CA202202020019_01.jpg?type=f194_109_blend"},{"title":"[주간아 4K캠] kep1er - WA DA DA (케플러 - 와다다) l EP.547","contents":"3:13","link":"https://tv.naver.com/v/24898159","retrieved":1643805119565,"image":"https://phinf.pstatic.net/tvcast/20220202_29/f7pha_1643798194116qY0KU_JPEG/CA202202020007_01.jpg?type=f194_109_blend"},{"title":"[주간아 짐벌캠] kep1er - WA DA DA (케플러 - 와다다) l EP.547","contents":"3:13","link":"https://tv.naver.com/v/24898057","retrieved":1643805119566,"image":"https://phinf.pstatic.net/tvcast/20220202_45/ph1Oe_1643797591088huR3G_JPEG/CA202202020018_01.jpg?type=f194_109_blend"},{"title":"[주간아 직캠] kep1er DAYEON - WA DA DA (케플러 김다연 - 와다다) l EP.547","contents":"3:10","link":"https://tv.naver.com/v/24898056","retrieved":1643805119567,"image":"https://phinf.pstatic.net/tvcast/20220202_150/Mfd44_1643797590077Ntd5h_JPEG/CA202202020010_01.jpg?type=f194_109_blend"},{"title":"[주간아 직캠] kep1er YESEO - WA DA DA (케플러 강예서 - 와다다) l EP.547","contents":"3:10","link":"https://tv.naver.com/v/24898009","retrieved":1643805119571,"image":"https://phinf.pstatic.net/tvcast/20220202_136/kB5TO_1643797293599qiy6t_JPEG/CA202202020009_01.jpg?type=f194_109_blend"},{"title":"[주간아 직캠] kep1er CHAEHYUN - WA DA DA (케플러 김채현 - 와다다) l EP.547","contents":"3:11","link":"https://tv.naver.com/v/24897862","retrieved":1643805119572,"image":"https://phinf.pstatic.net/tvcast/20220202_101/DYYlw_1643796394792okwsw_JPEG/CA202202020011_01.jpg?type=f194_109_blend"},{"title":"[주간아 직캠] kep1er HUENING BAHIYYIH - WA DA DA (케플러 휴닝바히에 - 와다다) l EP.547","contents":"3:10","link":"https://tv.naver.com/v/24897861","retrieved":1643805119574,"image":"https://phinf.pstatic.net/tvcast/20220202_262/yStrK_1643796393706eA14A_JPEG/CA202202020016_01.jpg?type=f194_109_blend"},{"title":"[주간아 직캠] kep1er YOUNGEUN - WA DA DA (케플러 서영은 - 와다다) l EP.547","contents":"3:10","link":"https://tv.naver.com/v/24897803","retrieved":1643805119576,"image":"https://phinf.pstatic.net/tvcast/20220202_20/xVXuZ_16437960932915zpLG_JPEG/CA202202020014_01.jpg?type=f194_109_blend"},{"title":"[주간아 직캠] kep1er MASHIRO - WA DA DA (케플러 마시로 - 와다다) l EP.547","contents":"3:11","link":"https://tv.naver.com/v/24897802","retrieved":1643805119579,"image":"https://phinf.pstatic.net/tvcast/20220202_61/whNlM_1643796092353B2Aye_JPEG/CA202202020012_01.jpg?type=f194_109_blend"},{"title":"[주간아 직캠] kep1er XIAOTING - WA DA DA (케플러 샤오팅 - 와다다) l EP.547","contents":"3:10","link":"https://tv.naver.com/v/24897760","retrieved":1643805119580,"image":"https://phinf.pstatic.net/tvcast/20220202_46/Jqyv2_1643795853258GqNJ5_JPEG/CA202202020013_01.jpg?type=f194_109_blend"},{"title":"[주간아 직캠] kep1er HIKARU - WA DA DA (케플러 히카루 - 와다다) l EP.547","contents":"3:10","link":"https://tv.naver.com/v/24897758","retrieved":1643805119581,"image":"https://phinf.pstatic.net/tvcast/20220202_11/EavFV_1643795852182kyQzE_JPEG/CA202202020017_01.jpg?type=f194_109_blend"}]}